<?xml version="1.0" encoding="utf-8"?>
<Defs>

    <!-- 镇暴棍 -->
    <ThingDef ParentName="WolfeinBaseMeleeBlunt">
        <defName>W_Weapon_Melee_Baton</defName>
        <label>Wolfein Riot Baton</label>
        <description>A low-lethality weapon used by the Wolfein for controlling riots and violent outbreaks. Crafted from durable materials, it's designed to suppress unrest without causing fatal harm.</description>
        <possessionCount>0</possessionCount>
        <graphicData>
            <texPath>Wolfein/Weapon/Baton</texPath>
            <graphicClass>Graphic_Single</graphicClass>
            <shaderType>CutoutComplex</shaderType>
        </graphicData>
        <uiIconScale>1</uiIconScale>
        <techLevel>Industrial</techLevel>
        <statBases>
            <WorkToMake>8000</WorkToMake>
            <Mass>1.25</Mass>
        </statBases>
        <equippedAngleOffset>-65</equippedAngleOffset>
        <recipeMaker>
            <researchPrerequisite>Wolfein_MeleeWeapon</researchPrerequisite>
            <recipeUsers Inherit="False">
                <li>ElectricSmithy</li>
            </recipeUsers>
            <skillRequirements>
                <Crafting>3</Crafting>
            </skillRequirements>
            <displayPriority>400</displayPriority>
        </recipeMaker>
        <costList>
            <Wolfein_AlloyMaterials>30</Wolfein_AlloyMaterials>
                    <Weapon_Parts>2</Weapon_Parts>
        </costList>
        <costStuffCount>20</costStuffCount>
        <stuffCategories>
            <li>Metallic</li>
        </stuffCategories>
        <weaponClasses>
            <li>Melee</li>
        </weaponClasses>
        <weaponTags>
            <li>Wolfein_M_WeaponII</li>
            <li>Wolfein_Baton</li>
        </weaponTags>
        <tools>
            <li>
                <label>handle</label>
                <capacities>
                    <li>Poke</li>
                </capacities>
                <power>8</power>
                <cooldownTime>2</cooldownTime>
                <armorPenetration>0.1</armorPenetration>
            </li>
            <li>
                <label>body</label>
                <labelUsedInLogging>false</labelUsedInLogging>
                <capacities>
                    <li>Blunt</li>
                </capacities>
                <power>12</power>
                <cooldownTime>1.6</cooldownTime>
                <armorPenetration>0.3</armorPenetration>
            </li>
        </tools>
    </ThingDef>

    <!-- 重型动力斧 -->
    <ThingDef ParentName="WolfeinBaseMeleeSharp">
        <defName>W_Weapon_Melee_HeavyPowerAxe</defName>
        <label>Wolfein Heavy Power Axe</label>
        <description>A colossal melee weapon occasionally deployed in close-quarters combat, utilizing advanced propulsion systems to deliver devastating kinetic strikes.</description>
        <possessionCount>0</possessionCount>
        <uiIconPath>Wolfein/Weapon/HeavyPoweraxe</uiIconPath>
        <graphicData>
            <texPath>Wolfein/Weapon/HeavyPoweraxe_OnHand</texPath>
            <graphicClass>Graphic_Single</graphicClass>
            <drawSize>1.5</drawSize>
            <shaderType>CutoutComplex</shaderType>
        </graphicData>
        <uiIconScale>1</uiIconScale>
        <techLevel>Industrial</techLevel>
        <relicChance>2</relicChance>
        <equippedAngleOffset>-65</equippedAngleOffset>
        <weaponClasses>
            <li>Melee</li>
        </weaponClasses>
        <weaponTags>
            <li>Wolfein_M_WeaponII</li>
            <li>Wolfein_HeavyPowerAxe</li>
        </weaponTags>
        <recipeMaker>
            <researchPrerequisite>Wolfein_MeleeWeapon</researchPrerequisite>
            <recipeUsers Inherit="False">
                <li>ElectricSmithy</li>
            </recipeUsers>
            <skillRequirements>
                <Crafting>5</Crafting>
            </skillRequirements>
            <displayPriority>420</displayPriority>
        </recipeMaker>
        <equippedStatOffsets>
            <MoveSpeed>-0.2</MoveSpeed>
        </equippedStatOffsets>
        <statBases>
            <WorkToMake>22000</WorkToMake>
            <Mass>10</Mass>
        </statBases>
        <costList>
            <Wolfein_AlloyMaterials>80</Wolfein_AlloyMaterials>
            <ComponentIndustrial>8</ComponentIndustrial>
                    <Weapon_Parts>3</Weapon_Parts>
        </costList>
        <costStuffCount>80</costStuffCount>
        <stuffCategories>
            <li>Metallic</li>
        </stuffCategories>
        <tools>
            <li>
                <label>handle</label>
                <capacities>
                    <li>Poke</li>
                </capacities>
                <power>10</power>
                <cooldownTime>1.8</cooldownTime>
                <armorPenetration>0.1</armorPenetration>
            </li>
            <li>
                <label>blade</label>
                <capacities>
                    <li>Cut</li>
                </capacities>
                <power>38</power>
                <cooldownTime>3.3</cooldownTime>
                <armorPenetration>0.9</armorPenetration>
            </li>
        </tools>
    </ThingDef>

    <!-- 巨型砍刀 -->
    <ThingDef ParentName="WolfeinBaseMeleeSharp">
        <defName>W_Weapon_Melee_HeavyMachete</defName>
        <label>Wolfein Heavy Machete</label>
        <description>Though cumbersome and unwieldy to operate, this monolithic blade becomes a terrifying force in the hands of skilled wielders, capable of cleaving through armor with brutal efficiency.</description>
        <possessionCount>0</possessionCount>
        <uiIconPath>Wolfein/Weapon/HeavyMachete</uiIconPath>
        <graphicData>
            <texPath>Wolfein/Weapon/HeavyMachete_OnHand</texPath>
            <graphicClass>Graphic_Single</graphicClass>
            <drawSize>1.5</drawSize>
            <shaderType>CutoutComplex</shaderType>
        </graphicData>
        <uiIconScale>1</uiIconScale>
        <techLevel>Industrial</techLevel>
        <relicChance></relicChance>
        <equippedAngleOffset></equippedAngleOffset>
        <weaponClasses>
            <li>Melee</li>
        </weaponClasses>
        <weaponTags>
            <li>Wolfein_M_WeaponII</li>
            <li>Wolfein_HeavyMachete</li>
        </weaponTags>
        <recipeMaker>
            <researchPrerequisite>Wolfein_MeleeWeapon</researchPrerequisite>
            <recipeUsers Inherit="False">
                <li>ElectricSmithy</li>
            </recipeUsers>
            <skillRequirements>
                <Crafting>5</Crafting>
            </skillRequirements>
            <displayPriority>420</displayPriority>
        </recipeMaker>
        <equippedStatOffsets>
            <MoveSpeed>-0.2</MoveSpeed>
        </equippedStatOffsets>
        <statBases>
            <WorkToMake>21000</WorkToMake>
            <Mass>8</Mass>
        </statBases>
        <costList>
            <Wolfein_AlloyMaterials>70</Wolfein_AlloyMaterials>
            <ComponentIndustrial>5</ComponentIndustrial>
                    <Weapon_Parts>3</Weapon_Parts>
        </costList>
        <costStuffCount>60</costStuffCount>
        <stuffCategories>
            <li>Metallic</li>
        </stuffCategories>
        <tools>
            <li>
                <label>handle</label>
                <capacities>
                    <li>Blunt</li>
                </capacities>
                <power>15</power>
                <cooldownTime>1.8</cooldownTime>
                <armorPenetration>0.1</armorPenetration>
            </li>
            <li>
                <label>edge</label>
                <capacities>
                    <li>Cut</li>
                </capacities>
                <power>30</power>
                <cooldownTime>2.5</cooldownTime>
                <armorPenetration>0.8</armorPenetration>
            </li>
        </tools>
    </ThingDef>

    <!-- 合金军刀 -->
    <ThingDef ParentName="WolfeinBaseMeleeSharp">
        <defName>W_Weapon_Melee_AlloySabre</defName>
        <label>Wolfein Alloy Sabre</label>
        <description>A seamless fusion of tradition and modernity, forged with Wolfein's advanced metallurgy and precision engineering to deliver surgical cutting precision and tactical striking power for versatile close-quarters engagements.</description>
        <possessionCount>0</possessionCount>
        <uiIconPath>Wolfein/Weapon/AlloySabre</uiIconPath>
        <graphicData>
            <texPath>Wolfein/Weapon/AlloySabre_OnHand</texPath>
            <graphicClass>Graphic_Single</graphicClass>
            <drawSize>1.5</drawSize>
            <shaderType>CutoutComplex</shaderType>
        </graphicData>
        <uiIconScale>1</uiIconScale>
        <techLevel>Industrial</techLevel>
        <relicChance></relicChance>
        <equippedAngleOffset></equippedAngleOffset>
        <weaponClasses>
            <li>Melee</li>
        </weaponClasses>
        <weaponTags>
            <li>Wolfein_M_WeaponII</li>
            <li>Wolfein_AlloySabre</li>
        </weaponTags>
        <recipeMaker>
            <researchPrerequisite>Wolfein_MeleeWeapon</researchPrerequisite>
            <recipeUsers Inherit="False">
                <li>ElectricSmithy</li>
            </recipeUsers>
            <skillRequirements>
                <Crafting>5</Crafting>
            </skillRequirements>
            <displayPriority>420</displayPriority>
        </recipeMaker>
        <statBases>
            <WorkToMake>18000</WorkToMake>
            <Mass>3</Mass>
        </statBases>
        <costList>
            <Wolfein_AlloyMaterials>65</Wolfein_AlloyMaterials>
            <ComponentIndustrial>2</ComponentIndustrial>
                    <Weapon_Parts>3</Weapon_Parts>
        </costList>
        <costStuffCount>40</costStuffCount>
        <stuffCategories>
            <li>Metallic</li>
        </stuffCategories>
        <tools>
            <li>
                <label>handle</label>
                <capacities>
                    <li>Blunt</li>
                </capacities>
                <power>10</power>
                <cooldownTime>1.6</cooldownTime>
                <armorPenetration>0.2</armorPenetration>
            </li>
            <li>
                <label>point</label>
                <capacities>
                    <li>Stab</li>
                </capacities>
                <power>24</power>
                <cooldownTime>2.4</cooldownTime>
            </li>
            <li>
                <label>edge</label>
                <capacities>
                    <li>Cut</li>
                </capacities>
                <power>24</power>
                <cooldownTime>2.4</cooldownTime>
            </li>
        </tools>
    </ThingDef>

    <!-- 合金匕首 -->
    <ThingDef ParentName="WolfeinBaseMeleeSharp">
        <defName>W_Weapon_Melee_AlloyDagger</defName>
        <label>Wolfein Alloy Dagger</label>
        <description>The standard-issue weapon of the Wolfein armed forces. Its modular, detachable blade design ensures that Wolfein elite soldiers remain sharp—until victory or death.</description>
        <possessionCount>0</possessionCount>
        <graphicData>
            <texPath>Wolfein/Weapon/AlloyDagger</texPath>
            <graphicClass>Graphic_Single</graphicClass>
            <drawSize>1.2</drawSize>
            <shaderType>CutoutComplex</shaderType>
        </graphicData>
        <uiIconScale>1</uiIconScale>
        <techLevel>Industrial</techLevel>
        <relicChance></relicChance>
        <equippedAngleOffset></equippedAngleOffset>
        <weaponClasses>
            <li>Melee</li>
        </weaponClasses>
        <weaponTags>
            <li>Wolfein_M_WeaponII</li>
            <li>Wolfein_AlloyDagger</li>
        </weaponTags>
        <recipeMaker>
            <researchPrerequisite>Wolfein_MeleeWeapon</researchPrerequisite>
            <recipeUsers Inherit="False">
                <li>ElectricSmithy</li>
            </recipeUsers>
            <skillRequirements>
                <Crafting>3</Crafting>
            </skillRequirements>
            <displayPriority>410</displayPriority>
        </recipeMaker>
        <statBases>
            <WorkToMake>20000</WorkToMake>
            <Mass>1.0</Mass>
        </statBases>
        <costList>
            <Wolfein_AlloyMaterials>10</Wolfein_AlloyMaterials>
            <ComponentIndustrial>1</ComponentIndustrial>
                    <Weapon_Parts>3</Weapon_Parts>
        </costList>
        <costStuffCount>40</costStuffCount>
        <stuffCategories>
            <li>Metallic</li>
        </stuffCategories>
        <tools>
            <li>
                <label>handle</label>
                <capacities>
                    <li>Blunt</li>
                </capacities>
                <power>10</power>
                <cooldownTime>2</cooldownTime>
                <armorPenetration>0.1</armorPenetration>
            </li>
            <li>
                <label>point</label>
                <capacities>
                    <li>Stab</li>
                </capacities>
                <power>14</power>
                <cooldownTime>1.4</cooldownTime>
                <armorPenetration>0.7</armorPenetration>
            </li>
            <li>
                <label>edge</label>
                <capacities>
                    <li>Cut</li>
                </capacities>
                <power>10</power>
                <cooldownTime>1.2</cooldownTime>
                <armorPenetration>0.5</armorPenetration>
            </li>
        </tools>
    </ThingDef>

    <!-- 重型军刀 -->
    <ThingDef ParentName="WolfeinBaseMeleeSharp">
        <defName>W_Weapon_Melee_HeavySabre</defName>
        <label>Wolfein Heavy Sabre</label>
        <description>A two-handed colossal blade with surprisingly manageable weight, delivering lethality comparable to bulkier melee weapons while maintaining sustained thrusting efficiency through its unique aerodynamic profile, earning the "Utility Knife" moniker among operatives.</description>
        <possessionCount>0</possessionCount>
        <uiIconPath>Wolfein/Weapon/HeavySabre</uiIconPath>
        <graphicData>
            <texPath>Wolfein/Weapon/HeavySabre_OnHand</texPath>
            <graphicClass>Graphic_Single</graphicClass>
            <drawSize>1.5</drawSize>
            <shaderType>CutoutComplex</shaderType>
        </graphicData>
        <uiIconScale>1</uiIconScale>
        <techLevel>Industrial</techLevel>
        <relicChance></relicChance>
        <equippedAngleOffset></equippedAngleOffset>
        <weaponClasses>
            <li>Melee</li>
        </weaponClasses>
        <weaponTags>
            <li>Wolfein_M_WeaponII</li>
            <li>Wolfein_HeavySabre</li>
        </weaponTags>
        <recipeMaker>
            <researchPrerequisite>Wolfein_MeleeWeapon</researchPrerequisite>
            <recipeUsers Inherit="False">
                <li>ElectricSmithy</li>
            </recipeUsers>
            <skillRequirements>
                <Crafting>5</Crafting>
            </skillRequirements>
            <displayPriority>420</displayPriority>
        </recipeMaker>
        <equippedStatOffsets>
            <MoveSpeed>-0.1</MoveSpeed>
        </equippedStatOffsets>
        <statBases>
            <WorkToMake>35000</WorkToMake>
            <Mass>6</Mass>
        </statBases>
        <costList>
            <Wolfein_AlloyMaterials>70</Wolfein_AlloyMaterials>
            <ComponentIndustrial>6</ComponentIndustrial>
                    <Weapon_Parts>3</Weapon_Parts>
        </costList>
        <costStuffCount>50</costStuffCount>
        <stuffCategories>
            <li>Metallic</li>
        </stuffCategories>
        <tools>
            <li>
                <label>handle</label>
                <capacities>
                    <li>Blunt</li>
                </capacities>
                <power>10</power>
                <cooldownTime>1.6</cooldownTime>
                <armorPenetration>0.25</armorPenetration>
            </li>
            <li>
                <label>point</label>
                <capacities>
                    <li>Stab</li>
                </capacities>
                <power>30</power>
                <cooldownTime>2.8</cooldownTime>
            </li>
            <li>
                <label>edge</label>
                <capacities>
                    <li>Cut</li>
                </capacities>
                <power>24</power>
                <cooldownTime>2.4</cooldownTime>
            </li>
        </tools>
    </ThingDef>

    <!-- 沃芬族简易匕首 -->
    <ThingDef ParentName="WolfeinBaseMeleeBlunt">
        <defName>W_Weapon_Melee_SimpleDagger</defName>
        <label>Wolfein Simple Dagger</label>
        <description>A ground iron shard with cloth-wrapped hilt, crudely assembled yet prevalent among Wolfein outcasts - those wolf-like vagrants prowling civilization's fringes.</description>
        <possessionCount>0</possessionCount>
        <graphicData>
            <texPath>Wolfein/Weapon/SimpleDagger</texPath>
            <graphicClass>Graphic_Single</graphicClass>
            <drawSize>1.2</drawSize>
            <shaderType>CutoutComplex</shaderType>
        </graphicData>
        <uiIconScale>1</uiIconScale>
        <techLevel>Medieval</techLevel>
        <statBases>
            <WorkToMake>1000</WorkToMake>
            <Mass>1</Mass>
        </statBases>
        <equippedAngleOffset>0</equippedAngleOffset>
        <recipeMaker>
            <researchPrerequisite>Wolfein_Weapon_I</researchPrerequisite>
            <recipeUsers Inherit="False">
                <li>ElectricSmithy</li>
                <li>CraftingSpot</li>
            </recipeUsers>
            <skillRequirements>
                <Crafting>2</Crafting>
            </skillRequirements>
            <displayPriority>400</displayPriority>
        </recipeMaker>
        <costList>
            <Wolfein_AlloyMaterials>3</Wolfein_AlloyMaterials>
                    <Weapon_Parts>2</Weapon_Parts>
        </costList>
        <weaponClasses>
            <li>Melee</li>
        </weaponClasses>
        <weaponTags>
            <li>Wolfein_M_WeaponI</li>
        </weaponTags>
        <tools>
            <li>
                <label>handle</label>
                <capacities>
                    <li>Blunt</li>
                </capacities>
                <power>6</power>
                <cooldownTime>2</cooldownTime>
            </li>
            <li>
                <label>point</label>
                <capacities>
                    <li>Stab</li>
                </capacities>
                <power>14</power>
                <cooldownTime>2</cooldownTime>
                <armorPenetration>0.25</armorPenetration>
            </li>
            <li>
                <label>edge</label>
                <capacities>
                    <li>Cut</li>
                </capacities>
                <power>10</power>
                <cooldownTime>1.5</cooldownTime>
                <armorPenetration>0.15</armorPenetration>
            </li>
        </tools>
    </ThingDef>

    <!-- 沃芬族简易长矛 -->
    <ThingDef ParentName="WolfeinBaseMeleeBlunt">
        <defName>W_Weapon_Melee_SimpleSpear</defName>
        <label>Wolfein Simple Spear</label>
        <description>A straight wooden shaft wrapped with leather at the grip and tipped with a dagger - this rudimentary yet timeless design remains the Wolfein's most ancient and pragmatic weapon. After all, classics never fade.</description>
        <possessionCount>0</possessionCount>
        <graphicData>
            <texPath>Wolfein/Weapon/SimpleSpear</texPath>
            <graphicClass>Graphic_Single</graphicClass>
            <drawSize>1.2</drawSize>
            <shaderType>CutoutComplex</shaderType>
        </graphicData>
        <uiIconScale>1</uiIconScale>
        <techLevel>Medieval</techLevel>
        <statBases>
            <WorkToMake>1200</WorkToMake>
            <Mass>1.5</Mass>
        </statBases>
        <equippedAngleOffset>0</equippedAngleOffset>
        <recipeMaker>
            <researchPrerequisite>Wolfein_Weapon_I</researchPrerequisite>
            <recipeUsers Inherit="False">
                <li>ElectricSmithy</li>
                <li>CraftingSpot</li>
            </recipeUsers>
            <skillRequirements>
                <Crafting>2</Crafting>
            </skillRequirements>
            <displayPriority>400</displayPriority>
        </recipeMaker>
        <costList>
            <WoodLog>10</WoodLog>
            <Wolfein_AlloyMaterials>3</Wolfein_AlloyMaterials>
                    <Weapon_Parts>2</Weapon_Parts>
        </costList>
        <weaponClasses>
            <li>Melee</li>
        </weaponClasses>
        <weaponTags>
            <li>Wolfein_M_WeaponI</li>
        </weaponTags>
        <tools>
            <li>
                <label>handle</label>
                <capacities>
                    <li>Blunt</li>
                </capacities>
                <power>8</power>
                <cooldownTime>2</cooldownTime>
                <armorPenetration>0.1</armorPenetration>
            </li>
            <li>
                <label>point</label>
                <capacities>
                    <li>Stab</li>
                </capacities>
                <power>18</power>
                <cooldownTime>2</cooldownTime>
                <armorPenetration>0.3</armorPenetration>
            </li>
        </tools>
    </ThingDef>

    <!-- 沃芬族铁丝棒球棍 -->
    <ThingDef ParentName="WolfeinBaseMeleeBlunt">
        <defName>W_Weapon_Melee_SimpleMace</defName>
        <label>Wolfein Simple Mace</label>
        <description>Whether salvaged from sports arenas or back-alley brawls, this baseball bat wrapped in razor wire now serves as a brutally pragmatic tool for "wilderness tourism".</description>
        <possessionCount>0</possessionCount>
        <graphicData>
            <texPath>Wolfein/Weapon/SimpleMace</texPath>
            <graphicClass>Graphic_Single</graphicClass>
            <drawSize>1.2</drawSize>
            <shaderType>CutoutComplex</shaderType>
        </graphicData>
        <uiIconScale>1</uiIconScale>
        <techLevel>Medieval</techLevel>
        <statBases>
            <WorkToMake>1200</WorkToMake>
            <Mass>1</Mass>
        </statBases>
        <equippedAngleOffset>0</equippedAngleOffset>
        <recipeMaker>
            <researchPrerequisite>Wolfein_Weapon_I</researchPrerequisite>
            <recipeUsers Inherit="False">
                <li>ElectricSmithy</li>
                <li>CraftingSpot</li>
            </recipeUsers>
            <skillRequirements>
                <Crafting>2</Crafting>
            </skillRequirements>
            <displayPriority>400</displayPriority>
        </recipeMaker>
        <costList>
            <WoodLog>20</WoodLog>
            <Wolfein_AlloyMaterials>2</Wolfein_AlloyMaterials>
                    <Weapon_Parts>2</Weapon_Parts>
        </costList>
        <weaponClasses>
            <li>Melee</li>
        </weaponClasses>
        <weaponTags>
            <li>Wolfein_M_WeaponI</li>
        </weaponTags>
        <tools>
            <li>
                <label>handle</label>
                <capacities>
                    <li>Poke</li>
                </capacities>
                <power>8</power>
                <cooldownTime>2</cooldownTime>
                <armorPenetration>0.1</armorPenetration>
            </li>
            <li>
                <label>body</label>
                <capacities>
                    <li>Blunt</li>
                </capacities>
                <power>15</power>
                <cooldownTime>1.8</cooldownTime>
                <armorPenetration>0.15</armorPenetration>
            </li>
        </tools>
    </ThingDef>

    <!-- 抵抗军合金匕首 -->
    <ThingDef ParentName="WolfeinBaseMeleeSharp">
        <defName>W_Weapon_Melee_RebelAlloyDagger</defName>
        <label>Wolfein Rebel Alloy Dagger</label>
        <description>The standard close-combat sidearm carried by Wolfein Resistance fighters, optimized for covert strikes and reliable armor-piercing efficiency.</description>
        <possessionCount>0</possessionCount>
        <graphicData>
            <texPath>Wolfein/Weapon/RebelAlloyDagger</texPath>
            <graphicClass>Graphic_Single</graphicClass>
            <drawSize>1.2</drawSize>
            <shaderType>CutoutComplex</shaderType>
        </graphicData>
        <uiIconScale>1</uiIconScale>
        <techLevel>Industrial</techLevel>
        <relicChance></relicChance>
        <equippedAngleOffset></equippedAngleOffset>
        <weaponClasses>
            <li>Melee</li>
        </weaponClasses>
        <weaponTags>
            <li>Wolfein_RebelAlloyDagger</li>
        </weaponTags>
        <recipeMaker>
            <researchPrerequisite>Wolfein_MeleeWeapon</researchPrerequisite>
            <recipeUsers Inherit="False">
                <li>ElectricSmithy</li>
            </recipeUsers>
            <skillRequirements>
                <Crafting>3</Crafting>
            </skillRequirements>
            <displayPriority>410</displayPriority>
        </recipeMaker>
        <statBases>
            <WorkToMake>17500</WorkToMake>
            <Mass>1.0</Mass>
        </statBases>
        <costStuffCount>50</costStuffCount>
        <stuffCategories>
            <li>Metallic</li>
        </stuffCategories>
        <tools>
            <li>
                <label>handle</label>
                <capacities>
                    <li>Blunt</li>
                </capacities>
                <power>9</power>
                <cooldownTime>2</cooldownTime>
                <armorPenetration>0.1</armorPenetration>
            </li>
            <li>
                <label>point</label>
                <capacities>
                    <li>Stab</li>
                </capacities>
                <power>14</power>
                <cooldownTime>1.6</cooldownTime>
                <armorPenetration>0.7</armorPenetration>
            </li>
            <li>
                <label>edge</label>
                <capacities>
                    <li>Cut</li>
                </capacities>
                <power>10</power>
                <cooldownTime>1.4</cooldownTime>
                <armorPenetration>0.4</armorPenetration>
            </li>
        </tools>
            <costList>
            <Weapon_Parts>3</Weapon_Parts>
        </costList>
    </ThingDef>

    <!-- AIPT链锯 -->
    <ThingDef ParentName="WolfeinBaseMeleeSharp">
        <defName>W_Weapon_Melee_AIPTChainSaw</defName>
        <label>Wolfein AIPT Chain Saw</label>
        <description>A heavy-duty weapon engineered by Wolfein Anomaly Intervention Teams for purging flesh-based entities, featuring armored housing with hyper-frequency vibrating teeth to rapidly disassemble non-humanoid biological structures.</description>
        <possessionCount>0</possessionCount>
        <uiIconPath>Wolfein/Weapon/AIPTChainSaw</uiIconPath>
        <graphicData>
            <texPath>Wolfein/Weapon/AIPTChainSaw_OnHand</texPath>
            <graphicClass>Graphic_Single</graphicClass>
            <drawSize>1.5</drawSize>
            <shaderType>CutoutComplex</shaderType>
        </graphicData>
        <uiIconScale>1</uiIconScale>
        <techLevel>Industrial</techLevel>
        <relicChance></relicChance>
        <equippedAngleOffset></equippedAngleOffset>
        <weaponClasses>
            <li>Melee</li>
        </weaponClasses>
        <weaponTags>
            <li>Wolfein_M_WeaponIII</li>
            <li>Wolfein_AIPTChainSaw</li>
        </weaponTags>
        <recipeMaker>
            <researchPrerequisites>
                <li>Wolfein_MeleeWeapon</li>
                <li>Wolfein_AIPTWeapon</li>
            </researchPrerequisites>
            <recipeUsers Inherit="False">
                <li>ElectricSmithy</li>
            </recipeUsers>
            <skillRequirements>
                <Crafting>5</Crafting>
            </skillRequirements>
            <displayPriority>420</displayPriority>
        </recipeMaker>
        <equippedStatOffsets>
            <MoveSpeed>-0.2</MoveSpeed>
        </equippedStatOffsets>
        <statBases>
            <WorkToMake>20000</WorkToMake>
            <Mass>8</Mass>
        </statBases>
        <costList>
            <Wolfein_AlloyMaterials>50</Wolfein_AlloyMaterials>
            <DepletedUranium>20</DepletedUranium>
            <ComponentIndustrial>6</ComponentIndustrial>
            <ComponentSpacer>1</ComponentSpacer>
                    <Weapon_Parts>3</Weapon_Parts>
        </costList>
        <costStuffCount>80</costStuffCount>
        <stuffCategories>
            <li>Metallic</li>
        </stuffCategories>
        <tools>
            <li>
                <label>blade</label>
                <capacities>
                    <li>Cut</li>
                </capacities>
                <power>12</power>
                <cooldownTime>0.8</cooldownTime>
                <armorPenetration>0.6</armorPenetration>
            </li>
        </tools>
    </ThingDef>
</Defs>